README.rst
setup.py
aliyun_voice/__init__.py
aliyun_voice/voice.py
aliyun_voice.egg-info/PKG-INFO
aliyun_voice.egg-info/SOURCES.txt
aliyun_voice.egg-info/dependency_links.txt
aliyun_voice.egg-info/requires.txt
aliyun_voice.egg-info/top_level.txt
test/test_aliyun.py