Metadata-Version: 1.1
Name: aliyun-voice
Version: 1.0.2
Summary: SDK for Aliyun tts service
Home-page: https://github.com/huyinghuan/aliyun-voice-py
Author: huyinghuan
Author-email: ec.huyinghuan@gmail.com
License: MIT
Keywords: aliyun voice tts sdk
Platform: UNKNOWN
Classifier: Development Status :: 5 - Production/Stable
Classifier: Intended Audience :: Developers
Classifier: Topic :: Software Development :: Libraries
Classifier: License :: OSI Approved :: MIT License
Classifier: Programming Language :: Python :: 2.7
